gridfix/__init__.py
gridfix/features.py
gridfix/model.py
gridfix/regionset.py
gridfix-0.3.2.dist-info/LICENSE.txt
gridfix-0.3.2.dist-info/METADATA
gridfix-0.3.2.dist-info/WHEEL
gridfix-0.3.2.dist-info/top_level.txt
gridfix-0.3.2.dist-info/zip-safe
gridfix-0.3.2.dist-info/RECORD
