Metadata-Version: 2.1
Name: gridfix
Version: 0.3.2
Summary: Parcellation-based gaze fixation preprocessing for GLMM analysis
Home-page: https://github.com/ischtz/gridfix
Author: Immo Schuetz
Author-email: schuetz.immo@gmail.com
License: MIT
Platform: UNKNOWN
Classifier: License :: OSI Approved :: MIT License
Classifier: Intended Audience :: Science/Research
Classifier: Operating System :: OS Independent
Classifier: Programming Language :: Python :: 3
Requires-Python: >=3.6
License-File: LICENSE.txt
Requires-Dist: numpy
Requires-Dist: matplotlib
Requires-Dist: scipy
Requires-Dist: pandas
